quantpyml/__init__.py
quantpyml/equity/__init__.py
quantpyml/equity/black_litterman.py
quantpyml/equity/black_scholes.py
quantpyml/equity/efficient_frontier.py
quantpyml/returns/__init__.py
quantpyml/returns/brownian_motion.py
quantpyml/returns/geometric_brownian_motion.py
quantpyml-0.0.2.dist-info/LICENSE
quantpyml-0.0.2.dist-info/METADATA
quantpyml-0.0.2.dist-info/WHEEL
quantpyml-0.0.2.dist-info/top_level.txt
quantpyml-0.0.2.dist-info/RECORD
