Metadata-Version: 2.1
Name: quantpyml
Version: 0.0.2
Summary: A package for quantitative finance with ML-based modeling tools
Author-email: Tejas Kamtam <tejaskamtam@yahoo.com>
License: MIT License
Project-URL: Homepage, https://github.com/tejaskamtam/quantpy-ml
Keywords: quant,finance,machine learning
Classifier: Development Status :: 3 - Alpha
Classifier: Intended Audience :: Developers
Classifier: Intended Audience :: Science/Research
Classifier: Programming Language :: Python :: 3
Classifier: License :: OSI Approved :: MIT License
Classifier: Operating System :: OS Independent
Classifier: Natural Language :: English
Classifier: Topic :: Scientific/Engineering :: Artificial Intelligence
Classifier: Topic :: Office/Business :: Financial
Classifier: Topic :: Office/Business :: Financial :: Investment
Classifier: License :: OSI Approved :: MIT License
Requires-Python: >=3.7
License-File: LICENSE
Requires-Dist: numpy
Requires-Dist: pandas
Requires-Dist: scipy
Requires-Dist: matplotlib
